metablock/__init__.py
metablock/cli.py
metablock/client.py
metablock/components.py
metablock/extensions.py
metablock/orgs.py
metablock/py.typed
metablock/spaces.py
metablock/user.py
metablock/utils.py
metablock-1.1.0.dist-info/LICENSE
metablock-1.1.0.dist-info/METADATA
metablock-1.1.0.dist-info/WHEEL
metablock-1.1.0.dist-info/entry_points.txt
metablock-1.1.0.dist-info/RECORD
