Metadata-Version: 2.3
Name: metablock
Version: 1.1.0
Summary: Metablock cloud python client
License: BSD
Author: Luca Sbardella
Author-email: luca@quantmind.com
Requires-Python: >=3.11
Classifier: License :: Other/Proprietary License
Classifier: Programming Language :: Python :: 3
Classifier: Programming Language :: Python :: 3.11
Classifier: Programming Language :: Python :: 3.12
Classifier: Programming Language :: Python :: 3.13
Provides-Extra: cli
Requires-Dist: click (>=8.1.7) ; extra == "cli"
Requires-Dist: httpx (>=0.28.1)
Requires-Dist: jinja2 (>=3.1.6) ; extra == "cli"
Requires-Dist: multidict (>=6.4.3)
Requires-Dist: pyyaml (>=6.0.2) ; extra == "cli"
